micropython_microbit_fs/__init__.py
micropython_microbit_fs/api.py
micropython_microbit_fs/cli.py
micropython_microbit_fs/device_info.py
micropython_microbit_fs/exceptions.py
micropython_microbit_fs/file.py
micropython_microbit_fs/filesystem.py
micropython_microbit_fs/flash_regions.py
micropython_microbit_fs/hex_utils.py
micropython_microbit_fs/hexes/microbitv1/v1.1.1/micropython-microbit-v1.1.1.hex
micropython_microbit_fs/hexes/microbitv2/v2.1.2/micropython-microbit-v2.1.2.hex
micropython_microbit_fs/hexes.py
micropython_microbit_fs/py.typed
micropython_microbit_fs/uicr.py
micropython_microbit_fs-0.1.1.dist-info/WHEEL
micropython_microbit_fs-0.1.1.dist-info/entry_points.txt
micropython_microbit_fs-0.1.1.dist-info/METADATA
micropython_microbit_fs-0.1.1.dist-info/RECORD
