Metadata-Version: 2.4
Name: micropython-microbit-fs
Version: 0.1.1
Summary: Library and cli app to add and extract files from MicroPython Hex files for micro:bit
Keywords: microbit,micropython,filesystem,intel-hex,embedded
Author: Carlos Pereira Atencio
Author-email: Carlos Pereira Atencio <carlosperate@embeddedlog.com>
License-Expression: MIT
Classifier: Development Status :: 4 - Beta
Classifier: Intended Audience :: Developers
Classifier: License :: OSI Approved :: MIT License
Classifier: Programming Language :: Python :: 3
Classifier: Programming Language :: Python :: 3.9
Classifier: Programming Language :: Python :: 3.10
Classifier: Programming Language :: Python :: 3.11
Classifier: Programming Language :: Python :: 3.12
Classifier: Programming Language :: Python :: 3.13
Classifier: Programming Language :: Python :: 3.14
Classifier: Topic :: Software Development :: Embedded Systems
Requires-Dist: cyclopts>=3.24.0
Requires-Dist: intelhex>=2.3.0
Requires-Dist: packaging>=21.0
Requires-Dist: ruff>=0.8.0 ; extra == 'dev'
Requires-Dist: pytest>=8.0.0 ; extra == 'dev'
Requires-Dist: pytest-cov>=4.0.0 ; extra == 'dev'
Requires-Dist: pytest-xdist>=3.0.0 ; extra == 'dev'
Requires-Dist: pytest-sugar>=1.0.0 ; extra == 'dev'
Requires-Dist: mypy>=1.0.0 ; extra == 'dev'
Requires-Dist: mini-racer>=0.12.4 ; extra == 'dev'
Requires-Python: >=3.9
Project-URL: Homepage, https://github.com/carlosperate/python-microbit-fs
Project-URL: Repository, https://github.com/carlosperate/python-microbit-fs.git
Project-URL: Issues, https://github.com/carlosperate/python-microbit-fs/issues
Project-URL: Changelog, https://github.com/carlosperate/python-microbit-fs/blob/main/CHANGELOG.md
Provides-Extra: dev
